[
  {
    "model": "leszek_app.Question",
    "fields": {
      "question": "Kt\u01f3ry z wymienionych zestaw\u00f3w potraw nale\u017cy zaplanowa\u0107 na przyj\u0119cie koktajlowe?",
      "answer_a": "\u017beberka grillowane, sa\u0142atka z burak\u00f3w, pyzy z mi\u0119sem.",
      "answer_b": "Tartinki, ptysie z pasztetem, koreczki \u015bledziowe.",
      "answer_c": "Krem z pieczarek, pstr\u0105g pieczony, sa\u0142atka caprese.",
      "answer_d": "Rolmopsy, steki wo\u0142owe, koktajl z krewetek.",
      "media": "",
      "code_id": 6
    }
  },
  {
    "model": "leszek_app.Question",
    "fields": {
      "question": "Kt\u00f3ry z podanych zestaw\u00f3w mi\u0119s jest odpowiedni do sporz\u0105dzania mi\u0119s po angielsku?",
      "answer_a": "Pol\u0119dwica i mostek.",
      "answer_b": "Mostek i \u0142opatka.",
      "answer_c": "Pol\u0119dwica i rostbef.",
      "answer_d": "Kark\u00f3wka i rostbef.",
      "media": "",
      "code_id": 5
    }
  },
  {
    "model": "leszek_app.Question",
    "fields": {
      "question": "Kt\u00f3r\u0105 technik\u0119 obr\u00f3bki termicznej przedstawiono w zamieszczonym materiale filmowym?",
      "answer_a": "Konfitowanie.",
      "answer_b": "Blanszowanie.",
      "answer_c": "Pra\u017cenie.",
      "answer_d": "Flambirowanie.",
      "media": "c4180000-5d77-0015-2e88-08d884ce4ee0.mp4",
      "code_id": 6
    }
  },
  {
    "model": "leszek_app.Question",
    "fields": {
      "question": "Kt\u00f3ry z wymienionych produkt\u00f3w nale\u017cy przechowywa\u0107 w warunkach ch\u0142odniczych?",
      "answer_a": "Olej rzepakowy.",
      "answer_b": "\u015aledzie solone.",
      "answer_c": "Ser twarogowy.",
      "answer_d": "Og\u00f3rki kiszone.",
      "media": "",
      "code_id": 5
    }
  },
  {
    "model": "leszek_app.Question",
    "fields": {
      "question": "Do serwowania jednej porcji zestawu obiadowego sk\u0142adaj\u0105cego si\u0119 z pieczonego pstr\u0105ga, ziemniak\u00f3w pur\u00e9e i sur\u00f3wki z kiszonej kapusty, kucharz powinien dobra\u0107",
      "answer_a": "talerz p\u0142aski \u2205 28 cm  i talerz p\u0142aski \u2205 19 cm.",
      "answer_b": "talerz p\u0142aski \u2205 19 cm i salaterk\u0119.",
      "answer_c": "talerz  p\u0142aski \u2205 21 cm i talerz p\u0142aski \u2205 17 cm.",
      "answer_d": "talerz p\u0142aski \u2205 28 cm i salaterk\u0119.",
      "media": "",
      "code_id": 5
    }
  },
  {
    "model": "leszek_app.Question",
    "fields": {
      "question": "Zadaniem Instytutu \u017bywno\u015bci i \u017bywienia jest",
      "answer_a": "badanie mikrobiologiczne pr\u00f3bek potraw pobranych w zak\u0142adach \u017cywienia zamkni\u0119tego.",
      "answer_b": "kontrolowanie warunk\u00f3w sanitarnych produkcji \u017cywno\u015bci.",
      "answer_c": "badanie sk\u0142adu i warto\u015bci od\u017cywczej \u017cywno\u015bci.",
      "answer_d": "kontrolowanie zawarto\u015bci soli w potrawach oferowanych przez sto\u0142\u00f3wki szkolne.",
      "media": "",
      "code_id": 6
    }
  },
  {
    "model": "leszek_app.Question",
    "fields": {
      "question": "Ser camembert powinien charakteryzowa\u0107 si\u0119 posmakiem pieczarek oraz",
      "answer_a": "porostem ple\u015bniowym i mi\u0119kkim, kremowym mi\u0105\u017cszem.",
      "answer_b": "porostem ple\u015bniowym i twardym, suchym mi\u0105\u017cszem.",
      "answer_c": "przerostem ple\u015bniowym i mi\u0119kkim, kremowym mi\u0105\u017cszem.",
      "answer_d": "przerostem ple\u015bniowym i twardym, suchym mi\u0105\u017cszem.",
      "media": "",
      "code_id": 6
    }
  },
  {
    "model": "leszek_app.Question",
    "fields": {
      "question": "Do grupy fizycznych metod utrwalania \u017cywno\u015bci nale\u017c\u0105",
      "answer_a": "zag\u0119szczanie i w\u0119dzenie.",
      "answer_b": "liofilizacja i ch\u0142odzenie.",
      "answer_c": "marynowanie i peklowanie.",
      "answer_d": "tyndalizacja i kiszenie.",
      "media": "",
      "code_id": 6
    }
  },
  {
    "model": "leszek_app.Question",
    "fields": {
      "question": "Kt\u00f3re z wymienionych dzia\u0142a\u0144 marketingowych zaplanowa\u0142 zak\u0142ad gastronomiczny, je\u017celi zaprosi\u0142 dziennikarzy na bal karnawa\u0142owy organizowany dla lokalnych biznesmen\u00f3w?",
      "answer_a": "Sprzeda\u017c osobist\u0105.",
      "answer_b": "Promocj\u0119 sprzeda\u017cy.",
      "answer_c": "Promocj\u0119 bezpo\u015bredni\u0105.",
      "answer_d": "Public relations.",
      "media": "",
      "code_id": 6
    }
  },
  {
    "model": "leszek_app.Question",
    "fields": {
      "question": "W \u017cywieniu osoby ze zlecon\u0105 diet\u0105 bogatoresztkow\u0105 nale\u017cy zwi\u0119kszy\u0107 poda\u017c",
      "answer_a": "bia\u0142ka zwierz\u0119cego.",
      "answer_b": "t\u0142uszcz\u00f3w ro\u015blinnych.",
      "answer_c": "b\u0142onnika pokarmowego.",
      "answer_d": "w\u0119glowodan\u00f3w prostych.",
      "media": "",
      "code_id": 6
    }
  },
  {
    "model": "leszek_app.Question",
    "fields": {
      "question": "Do kt\u00f3rej grupy sk\u0142adnik\u00f3w pokarmowych nale\u017cy kwas szczawiowy?",
      "answer_a": "Od\u017cywczych.",
      "answer_b": "Budulcowych.",
      "answer_c": "Nieod\u017cywczych.",
      "answer_d": "Energetycznych.",
      "media": "",
      "code_id": 6
    }
  },
  {
    "model": "leszek_app.Question",
    "fields": {
      "question": "Kt\u00f3ry z wymienionych b\u0142\u0119d\u00f3w pope\u0142niono w ca\u0142odziennym jad\u0142ospisie zamieszczonym w tabeli?",
      "answer_a": "Nie uwzgl\u0119dniono potraw z mi\u0119sa.",
      "answer_b": "Zaplanowano 2 potrawy z sera twarogowego.",
      "answer_c": "Zaplanowano 2 potrawy z burak\u00f3w \u0107wik\u0142owych.",
      "answer_d": "Nie uwzgl\u0119dniono potraw z ziemniak\u00f3w.",
      "media": "f0730000-bb04-7aea-c285-08dba39df109.jpg",
      "code_id": 6
    }
  },
  {
    "model": "leszek_app.Question",
    "fields": {
      "question": "Na kt\u00f3rej ilustracji przedstawiony jest n\u00f3\u017c do filetowania?",
      "answer_a": "Na ilustracji 2.",
      "answer_b": "Na ilustracji 4.",
      "answer_c": "Na ilustracji 1.",
      "answer_d": "Na ilustracji 3.",
      "media": "f0730000-bb04-7aea-8f2c-08db9cbb086c.jpg",
      "code_id": 6
    }
  },
  {
    "model": "leszek_app.Question",
    "fields": {
      "question": "Kt\u00f3rego sprz\u0119tu nale\u017cy u\u017cy\u0107 do duszenia du\u017cej ilo\u015bci mi\u0119sa wieprzowego na gulasz?",
      "answer_a": "Griddle grilla.",
      "answer_b": "Frytkownicy.",
      "answer_c": "Patelni uchylnej.",
      "answer_d": "Warnika.",
      "media": "",
      "code_id": 5
    }
  },
  {
    "model": "leszek_app.Question",
    "fields": {
      "question": "Korzystaj\u0105c z informacji zamieszczonych w tabeli wska\u017c, kt\u00f3ra witamina wyst\u0119puje w 100 g czarnej porzeczki w najwi\u0119kszej ilo\u015bci.",
      "answer_a": "Tokoferol.",
      "answer_b": "Retinol.",
      "answer_c": "Kwas askorbinowy.",
      "answer_d": "Kwas pantotenowy.",
      "media": "f0730000-bb04-7aea-0f8b-08dae134ae5a.jpg",
      "code_id": 6
    }
  },
  {
    "model": "leszek_app.Question",
    "fields": {
      "question": "Restauracja wprowadzaj\u0105c obni\u017ck\u0119 ceny balu studni\u00f3wkowego organizowanego w pi\u0105tek stosuje",
      "answer_a": "reklam\u0119.",
      "answer_b": "marketing bezpo\u015bredni.",
      "answer_c": "sponsoring.",
      "answer_d": "promocj\u0119 sprzeda\u017cy.",
      "media": "",
      "code_id": 6
    }
  },
  {
    "model": "leszek_app.Question",
    "fields": {
      "question": "Na podstawie danych zamieszczonych w tabeli, oblicz ca\u0142kowit\u0105 przemian\u0119 materii (CPM) dla m\u0119\u017cczyzny prowadz\u0105cego umiarkowan\u0105 aktywno\u015b\u0107 zawodow\u0105 i du\u017c\u0105 aktywno\u015b\u0107 pozazawodow\u0105, kt\u00f3rego podstawowa przemiana materii (PPM) wynosi 1 750 kcal/dob\u0119.",
      "answer_a": "3 150 kcal/dob\u0119",
      "answer_b": "2 625 kcal/dob\u0119",
      "answer_c": "2 800 kcal/dob\u0119",
      "answer_d": "3 325 kcal/dob\u0119",
      "media": "f0730000-bb04-7aea-f8ef-08dae135784e.jpg",
      "code_id": 6
    }
  },
  {
    "model": "leszek_app.Question",
    "fields": {
      "question": "Kt\u00f3rego zestawu produkt\u00f3w nale\u017cy u\u017cy\u0107 do sporz\u0105dzenia sosu \u201etzatziki\u201d?",
      "answer_a": "Majonez, og\u00f3rki, grzyby marynowane.",
      "answer_b": "Olej, cebula, przecier pomidorowy.",
      "answer_c": "Jogurt, czosnek, \u015bwie\u017ce og\u00f3rki.",
      "answer_d": "Olej, \u017c\u00f3\u0142tka, sok z cytryny.",
      "media": "",
      "code_id": 5
    }
  },
  {
    "model": "leszek_app.Question",
    "fields": {
      "question": "N\u00f3\u017c przedstawiony na ilustracji przeznaczony jest do rozdrabniania",
      "answer_a": "mi\u0119sa.",
      "answer_b": "zi\u00f3\u0142.",
      "answer_c": "sera.",
      "answer_d": "owoc\u00f3w.",
      "media": "24480000-5d64-0015-33e9-08d90bd7c4cb.PNG",
      "code_id": 5
    }
  },
  {
    "model": "leszek_app.Question",
    "fields": {
      "question": "Na podstawie zamieszczonego wykresu sprzeda\u017cy ch\u0142odnika w ci\u0105gu roku okre\u015bl, w kt\u00f3rym kwartale roku nale\u017cy wprowadzi\u0107 t\u0119 potraw\u0119 do menu restauracji.",
      "answer_a": "W czwartym kwartale.",
      "answer_b": "W drugim kwartale.",
      "answer_c": "W trzecim kwartale.",
      "answer_d": "W pierwszym kwartale.",
      "media": "f0730000-bb04-7aea-38b1-08d94780b199.jpg",
      "code_id": 6
    }
  },
  {
    "model": "leszek_app.Question",
    "fields": {
      "question": "Ile sztuk jaj o masie 50 g zast\u0105pi 1,2 kg sera homogenizowanego, je\u017celi zgodnie z tabel\u0105 zamiany produkt\u00f3w 100 g jaj zast\u0119puje 200 g sera homogenizowanego?",
      "answer_a": "12 szt.",
      "answer_b": "18 szt.",
      "answer_c": "6 szt.",
      "answer_d": "24 szt.",
      "media": "",
      "code_id": 6
    }
  },
  {
    "model": "leszek_app.Question",
    "fields": {
      "question": "Oblicz wysoko\u015b\u0107 bud\u017cetu, kt\u00f3rym musi dysponowa\u0107 restauracja, aby zrealizowa\u0107 zam\u00f3wienie na 450 porcji uszek z grzybami, je\u017celi koszt zakupu surowc\u00f3w na 10 porcji wynosi 1,20 z\u0142, a pozosta\u0142e koszty produkcji 10 porcji uszek wynosz\u0105 1,00 z\u0142.",
      "answer_a": "99,00 z\u0142",
      "answer_b": "45,00 z\u0142",
      "answer_c": "54,00 z\u0142",
      "answer_d": "90,00 z\u0142",
      "media": "",
      "code_id": 5
    }
  },
  {
    "model": "leszek_app.Question",
    "fields": {
      "question": "Ga\u015bnic\u0119 posiadaj\u0105c\u0105 na etykiecie znak przedstawiony na ilustracji nale\u017cy stosowa\u0107 do gaszenia pal\u0105cych si\u0119",
      "answer_a": "t\u0142uszcz\u00f3w.",
      "answer_b": "przedmiot\u00f3w drewnianych.",
      "answer_c": "gaz\u00f3w.",
      "answer_d": "przedmiot\u00f3w metalowych.",
      "media": "24480000-5d64-0015-df17-08d90bccb74b.PNG",
      "code_id": 5
    }
  },
  {
    "model": "leszek_app.Question",
    "fields": {
      "question": "Przy kt\u00f3rej z wymienionych potraw w karcie menu nale\u017cy umie\u015bci\u0107 informacj\u0119 o obecno\u015bci alergen\u00f3w pochodz\u0105cych ze skorupiak\u00f3w?",
      "answer_a": "Kalmary w tempurze.",
      "answer_b": "Tagliatelle z omu\u0142kami.",
      "answer_c": "Przegrzebki w \u015bmietanie.",
      "answer_d": "Risotto z langust\u0105.",
      "media": "",
      "code_id": 6
    }
  },
  {
    "model": "leszek_app.Question",
    "fields": {
      "question": "Granitor przedstawiony na ilustracji przeznaczony jest",
      "answer_a": "do sporz\u0105dzania sorbet\u00f3w.",
      "answer_b": "do parzenia kawy.",
      "answer_c": "do wyciskania cytrus\u00f3w.",
      "answer_d": "do podgrzewania czekolady.",
      "media": "24480000-5d64-0015-812b-08d90bd5dd99.PNG",
      "code_id": 5
    }
  },
  {
    "model": "leszek_app.Question",
    "fields": {
      "question": "Ile talerzy p\u0142askich \u00d8 21 cm nale\u017cy przygotowa\u0107 na bankiet angielski dla 130 os\u00f3b, uwzgl\u0119dniaj\u0105c 120 % zapas?",
      "answer_a": "286 sztuk.",
      "answer_b": "276 sztuk.",
      "answer_c": "136 sztuk.",
      "answer_d": "156 sztuk.",
      "media": "",
      "code_id": 6
    }
  },
  {
    "model": "leszek_app.Question",
    "fields": {
      "question": "W 100 g zasma\u017canego szpinaku znajduje si\u0119 120 mg wapnia. O ile miligram\u00f3w wapnia wzbogacony zostanie omlet naturalny, gdy doda si\u0119 do niego 150 g zasma\u017canego szpinaku?",
      "answer_a": "270 mg",
      "answer_b": "370 mg",
      "answer_c": "180 mg",
      "answer_d": "250 mg",
      "media": "",
      "code_id": 6
    }
  },
  {
    "model": "leszek_app.Question",
    "fields": {
      "question": "Kt\u00f3re zio\u0142o przedstawione jest na ilustracji?",
      "answer_a": "Sza\u0142wia.",
      "answer_b": "Rozmaryn.",
      "answer_c": "Lubczyk.",
      "answer_d": "Melisa.",
      "media": "f0730000-bb04-7aea-1d77-08db9cb64540.jpg",
      "code_id": 6
    }
  },
  {
    "model": "leszek_app.Question",
    "fields": {
      "question": "\u017bywienie dzieci w przedszkolu powinno pokry\u0107 75 % dziennego zapotrzebowania na sk\u0142adniki od\u017cywcze. Oblicz, ile w\u0119glowodan\u00f3w nale\u017cy zaplanowa\u0107 w jad\u0142ospisie dla jednego dziecka, je\u017celi dzienna norma wynosi 130 g.",
      "answer_a": "6,50 g",
      "answer_b": "97,50 g",
      "answer_c": "65,00 g",
      "answer_d": "9,75 g",
      "media": "",
      "code_id": 6
    }
  },
  {
    "model": "leszek_app.Question",
    "fields": {
      "question": "Urz\u0105dzenie przedstawione na ilustracji jest przeznaczone do",
      "answer_a": "sma\u017cenia nale\u015bnik\u00f3w.",
      "answer_b": "grillowania warzyw.",
      "answer_c": "sma\u017cenia kotlet\u00f3w.",
      "answer_d": "grillowania kie\u0142basy.",
      "media": "f0730000-bb04-7aea-444c-08dae1379fa1.jpg",
      "code_id": 6
    }
  },
  {
    "model": "leszek_app.Question",
    "fields": {
      "question": "Kt\u00f3ry z wymienionych dodatk\u00f3w witaminowych nale\u017cy zastosowa\u0107 do uzupe\u0142nienia zestawu potraw sk\u0142adaj\u0105cego si\u0119 z barszczu czerwonego, kotleta z soi i ziemniak\u00f3w z wody?",
      "answer_a": "Buraki zasma\u017cane.",
      "answer_b": "B\u00f3b gotowany.",
      "answer_c": "Sur\u00f3wk\u0119 z marchwi.",
      "answer_d": "\u0106wik\u0142\u0119 z chrzanem.",
      "media": "",
      "code_id": 6
    }
  },
  {
    "model": "leszek_app.Question",
    "fields": {
      "question": "G\u0119sta konsystencja, lekko dro\u017cd\u017cowy zapach i kwaskowy smak to  cechy charakterystyczne",
      "answer_a": "\u015bmietanki.",
      "answer_b": "mleka acidofilnego.",
      "answer_c": "ma\u015blanki spo\u017cywczej.",
      "answer_d": "kefiru.",
      "media": "",
      "code_id": 6
    }
  },
  {
    "model": "leszek_app.Question",
    "fields": {
      "question": "Na podstawie danych zamieszczonych w tabeli, okre\u015bl dobowe zapotrzebowanie na fosfor i magnez dla 21-letniej ci\u0119\u017carnej kobiety.",
      "answer_a": "Fosfor 1250 mg, magnez 360 mg",
      "answer_b": "Fosfor 700 mg, magnez 320 mg",
      "answer_c": "Fosfor 700 mg, magnez 360 mg",
      "answer_d": "Fosfor 1250 mg, magnez 400 mg",
      "media": "47ec0000-f683-928a-0f98-08dbf7b83eaf.jpg",
      "code_id": 6
    }
  },
  {
    "model": "leszek_app.Question",
    "fields": {
      "question": "Przestawiony na ilustracji znak zamieszczony na butelce ze \u015brodkiem do czyszczenia oznacza, \u017ce zawiera ona",
      "answer_a": "substancj\u0119 \u017cr\u0105c\u0105.",
      "answer_b": "substancj\u0119 neutralizuj\u0105c\u0105.",
      "answer_c": "mieszanin\u0119 wody i t\u0142uszczu.",
      "answer_d": "mieszanin\u0119 wody i benzyny.",
      "media": "24480000-5d64-0015-f619-08d90bcc1883.PNG",
      "code_id": 5
    }
  },
  {
    "model": "leszek_app.Question",
    "fields": {
      "question": "Jednym z zada\u0144 pracownik\u00f3w stacji sanitarno-epidemiologicznej jest kontrola",
      "answer_a": "pr\u00f3bek pokarmowych ze sto\u0142\u00f3wek szkolnych.",
      "answer_b": "prawid\u0142owego rozliczania podatku VAT.",
      "answer_c": "ilo\u015bci zakupionego sprz\u0119tu do restauracji.",
      "answer_d": "przestrzegania przepis\u00f3w prawa pracy.",
      "media": "",
      "code_id": 6
    }
  },
  {
    "model": "leszek_app.Question",
    "fields": {
      "question": "Do kt\u00f3rego z pojemnik\u00f3w przedstawionych na ilustracjach nale\u017cy zapakowa\u0107 na wynos zestaw obiadowy sk\u0142adaj\u0105cy si\u0119 z gulaszu wieprzowego i ry\u017cu z warzywami?",
      "answer_a": "Do pojemnika 4.",
      "answer_b": "Do pojemnika 3.",
      "answer_c": "Do pojemnika 1.",
      "answer_d": "Do pojemnika 2.",
      "media": "f0730000-bb04-7aea-ce05-08db98d08940.jpg",
      "code_id": 6
    }
  },
  {
    "model": "leszek_app.Question",
    "fields": {
      "question": "Kt\u00f3ry z wymienionych zestaw\u00f3w potraw nale\u017cy zaplanowa\u0107 na przyj\u0119cie o charakterze w\u0142oskim?",
      "answer_a": "Tortilla z kurczakiem, paella, churros.",
      "answer_b": "Bliny z kawiorem, rossolnik, pielmieni.",
      "answer_c": "Sa\u0142atka nicejska, ratatouille, zupa cebulowa.",
      "answer_d": "Sa\u0142atka caprese, penne z pomidorami, ossobuco.",
      "media": "",
      "code_id": 6
    }
  },
  {
    "model": "leszek_app.Question",
    "fields": {
      "question": "Przedstawiony na ilustracji spos\u00f3b formowania stosuje si\u0119 do sporz\u0105dzania",
      "answer_a": "ko\u0142dun\u00f3w.",
      "answer_b": "gnocchi.",
      "answer_c": "focacci.",
      "answer_d": "\u0142azanek.",
      "media": "24480000-5d64-0015-eab4-08d90bd55206.PNG",
      "code_id": 5
    }
  },
  {
    "model": "leszek_app.Question",
    "fields": {
      "question": "Urz\u0105dzenie przedstawione na ilustracji jest przeznaczone do",
      "answer_a": "dystrybucji napoj\u00f3w gor\u0105cych.",
      "answer_b": "przechowywania napoj\u00f3w zimnych.",
      "answer_c": "dystrybucji zupy gor\u0105cej. ",
      "answer_d": "przechowywania zupy zimnej.",
      "media": "f0730000-bb04-7aea-8a1d-08dae1340fd0.jpg",
      "code_id": 6
    }
  },
  {
    "model": "leszek_app.Question",
    "fields": {
      "question": "Podczas wykonywania prac porz\u0105dkowych do oka kucharza dosta\u0142 si\u0119 \u015brodek dezynfekcyjny. Udzielaj\u0105c mu pomocy w pierwszej kolejno\u015bci nale\u017cy",
      "answer_a": "przemy\u0107 oko ciep\u0142ym naparem z rumianku.",
      "answer_b": "posmarowa\u0107 oko ma\u015bci\u0105 do oczu.",
      "answer_c": "przemy\u0107 oko zimn\u0105 bie\u017c\u0105c\u0105 wod\u0105.",
      "answer_d": "zakropi\u0107 oko wod\u0105 utlenion\u0105.",
      "media": "",
      "code_id": 6
    }
  },
  {
    "model": "leszek_app.Question",
    "fields": {
      "question": "Z kt\u00f3rego powodu kasza w czasie gotowania zwi\u0119ksza swoj\u0105 obj\u0119to\u015b\u0107?",
      "answer_a": "Bia\u0142ka gliadyna i glutenina z wrz\u0105c\u0105 wod\u0105 tworz\u0105 gluten.",
      "answer_b": "Skrobia ulega hydrolizie i przebiega proces fermentacji.",
      "answer_c": "Bia\u0142ko wi\u0105\u017ce wod\u0119 i ulega rozklejeniu.",
      "answer_d": "Skrobia wi\u0105\u017ce wod\u0119 i ulega rozklejeniu.",
      "media": "",
      "code_id": 5
    }
  },
  {
    "model": "leszek_app.Question",
    "fields": {
      "question": "Kt\u00f3ry element kulinarny pochodzi z tuszy jagni\u0119cej?",
      "answer_a": "\u0141ata.",
      "answer_b": "Rostbef.",
      "answer_c": "Comber.",
      "answer_d": "Schab.",
      "media": "",
      "code_id": 5
    }
  },
  {
    "model": "leszek_app.Question",
    "fields": {
      "question": "Ile czasu potrzeba do przygotowania 55 nale\u015bnik\u00f3w z d\u017cemem, je\u017celi czas sporz\u0105dzenia jednego nale\u015bnika z nadzieniem wynosi 2 minuty?",
      "answer_a": "275 minut.",
      "answer_b": "330 minut.",
      "answer_c": "110 minut.",
      "answer_d": "165 minut.",
      "media": "",
      "code_id": 6
    }
  },
  {
    "model": "leszek_app.Question",
    "fields": {
      "question": "Kt\u00f3r\u0105 metod\u0119 obr\u00f3bki wst\u0119pnej z wykorzystaniem s\u0142oniny, nale\u017cy zastosowa\u0107 do przygotowania sztufady wo\u0142owej?",
      "answer_a": "Tablerowanie.",
      "answer_b": "Szpikowanie.",
      "answer_c": "Peklowanie.",
      "answer_d": "Bejcowanie.",
      "media": "",
      "code_id": 6
    }
  },
  {
    "model": "leszek_app.Question",
    "fields": {
      "question": "Kt\u00f3rej d\u0142ugo\u015bci st\u00f3\u0142 w kszta\u0142cie litery I nale\u017cy przygotowa\u0107 dla 30 os\u00f3b, je\u017celi odleg\u0142o\u015b\u0107 od kraw\u0119dzi sto\u0142u do \u015brodka pierwszego nakrycia wynosi 45 cm, odleg\u0142o\u015b\u0107 mi\u0119dzy \u015brodkami s\u0105siaduj\u0105cych nakry\u0107 wynosi 75 cm, a go\u015bcie usadzeni s\u0105 po obu stronach sto\u0142u?",
      "answer_a": "21,4 m",
      "answer_b": "42,8 m",
      "answer_c": "11,4 m",
      "answer_d": "22,8 m",
      "media": "",
      "code_id": 6
    }
  },
  {
    "model": "leszek_app.Question",
    "fields": {
      "question": "Kt\u00f3ry rodzaj obr\u00f3bki termicznej ma najwi\u0119kszy wp\u0142yw na obni\u017cenie strawno\u015bci mi\u0119sa surowej ryby?",
      "answer_a": "Sma\u017cenie zanurzeniowe.",
      "answer_b": "Duszenie bez obsma\u017cania.",
      "answer_c": "Pieczenie w r\u0119kawie.",
      "answer_d": "Gotowanie sous vide.",
      "media": "",
      "code_id": 6
    }
  },
  {
    "model": "leszek_app.Question",
    "fields": {
      "question": "Na kt\u00f3rej ilustracji przedstawiony jest prawid\u0142owy spos\u00f3b ustawienia sto\u0142u weselnego dla 60 os\u00f3b w sali o wymiarach 12 m x 25 m?",
      "answer_a": "Na ilustracji 1.",
      "answer_b": "Na ilustracji 3.",
      "answer_c": "Na ilustracji 4.",
      "answer_d": "Na ilustracji 2.",
      "media": "f0730000-bb04-7aea-6950-08db98cf736b.jpg",
      "code_id": 6
    }
  },
  {
    "model": "leszek_app.Question",
    "fields": {
      "question": "Ile gram\u00f3w m\u0105ki nale\u017cy u\u017cy\u0107 do zag\u0119szczenia 1 porcji zupy grzybowej, je\u017celi do 300 porcji zupy potrzeba 0,9 kg m\u0105ki?",
      "answer_a": "30 g",
      "answer_b": "3 g",
      "answer_c": "90 g",
      "answer_d": "9 g",
      "media": "",
      "code_id": 6
    }
  },
  {
    "model": "leszek_app.Question",
    "fields": {
      "question": "Na podstawie sk\u0142adnik\u00f3w wymienionych w zamieszczonym normatywie surowcowym wska\u017c metod\u0119, kt\u00f3r\u0105 nale\u017cy zastosowa\u0107 do utrwalenia dyni.",
      "answer_a": "Marynowanie.",
      "answer_b": "Kwaszenie.",
      "answer_c": "Liofilizacj\u0119.",
      "answer_d": "Pasteryzacj\u0119.",
      "media": "47ec0000-f683-928a-a445-08dbc96d83b8.jpg",
      "code_id": 5
    }
  },
  {
    "model": "leszek_app.Question",
    "fields": {
      "question": "Obr\u00f3bka termiczna, kt\u00f3rej nale\u017cy podda\u0107 rozdrobnione mi\u0119so z kurczaka i warzywa podczas sporz\u0105dzania potrawki z drobiu, to",
      "answer_a": "gotowanie.",
      "answer_b": "duszenie.",
      "answer_c": "sma\u017cenie.",
      "answer_d": "pieczenie.",
      "media": "",
      "code_id": 5
    }
  },
  {
    "model": "leszek_app.Question",
    "fields": {
      "question": "Kt\u00f3r\u0105 w\u0142a\u015bciwo\u015b\u0107 jaj wykorzystuje si\u0119 przy sporz\u0105dzaniu sufletu czekoladowego?",
      "answer_a": "Emulguj\u0105c\u0105.",
      "answer_b": "Spulchniaj\u0105c\u0105.",
      "answer_c": "Wi\u0105\u017c\u0105c\u0105.",
      "answer_d": "Zag\u0119szczaj\u0105c\u0105.",
      "media": "",
      "code_id": 5
    }
  },
  {
    "model": "leszek_app.Question",
    "fields": {
      "question": "Glukoza w organizmie cz\u0142owieka pe\u0142ni rol\u0119",
      "answer_a": "reguluj\u0105c\u0105.",
      "answer_b": "energetyczn\u0105.",
      "answer_c": "budulcow\u0105.",
      "answer_d": "stabilizuj\u0105c\u0105.",
      "media": "",
      "code_id": 6
    }
  },
  {
    "model": "leszek_app.Question",
    "fields": {
      "question": "Kt\u00f3re urz\u0105dzenie przedstawione jest na ilustracji?",
      "answer_a": "Grill do hot dog\u00f3w.",
      "answer_b": "Taboret elektryczny.",
      "answer_c": "Grill z p\u0142yt\u0105 ceramiczn\u0105.",
      "answer_d": "Ro\u017cen pionowy.",
      "media": "24480000-5d64-0015-e491-08d90bd5a7ad.PNG",
      "code_id": 5
    }
  },
  {
    "model": "leszek_app.Question",
    "fields": {
      "question": "Produkty spo\u017cywcze oznaczone znakiem przedstawionym na ilustracji s\u0105 przeznaczone dla os\u00f3b",
      "answer_a": "z cukrzyc\u0105 dietozale\u017cn\u0105.",
      "answer_b": "z nietolerancj\u0105 glutenu.",
      "answer_c": "z oty\u0142o\u015bci\u0105 olbrzymi\u0105.",
      "answer_d": "z nadci\u015bnieniem t\u0119tniczym.",
      "media": "",
      "code_id": 6
    }
  },
  {
    "model": "leszek_app.Question",
    "fields": {
      "question": "Kt\u00f3ry deser nale\u017cy zaplanowa\u0107 w ofercie restauracji realizuj\u0105cej program W\u0119gierskie smako\u0142yki?",
      "answer_a": "Pudding.",
      "answer_b": "Tiramisu.",
      "answer_c": "Nale\u015bniki Suzette.",
      "answer_d": "Nale\u015bniki \u00e0 la Gundel.",
      "media": "",
      "code_id": 6
    }
  },
  {
    "model": "leszek_app.Question",
    "fields": {
      "question": "Kt\u00f3rego etapu wykonania potraw mi\u0119snych brakuje w tabeli, w miejscu oznaczonym znakiem zapytania?",
      "answer_a": "Obr\u00f3bki wst\u0119pnej.",
      "answer_b": "Zamra\u017cania surowca.",
      "answer_c": "Obr\u00f3bki termicznej.",
      "answer_d": "Porcjowania wyrobu.",
      "media": "24480000-5d64-0015-d1fe-08d90bdb2b0d.PNG",
      "code_id": 5
    }
  },
  {
    "model": "leszek_app.Question",
    "fields": {
      "question": "Koszt brutto organizacji bankietu wynosi 2 500,00 z\u0142. Klient otrzyma\u0142 10 % rabatu. Oblicz zadatek brutto w wysoko\u015bci 20 %, kt\u00f3ry powinien wp\u0142aci\u0107 zleceniodawca us\u0142ugi.",
      "answer_a": "500,00 z\u0142",
      "answer_b": "450,00 z\u0142",
      "answer_c": "550,00 z\u0142",
      "answer_d": "495,00 z\u0142",
      "media": "",
      "code_id": 6
    }
  },
  {
    "model": "leszek_app.Question",
    "fields": {
      "question": "Organizuj\u0105c stanowisko do sma\u017cenia kotlet\u00f3w mielonych pracownik powinien przygotowa\u0107",
      "answer_a": "patelni\u0119 i kuter.",
      "answer_b": "salamander i \u0142opatk\u0119.",
      "answer_c": "patelni\u0119 i \u0142opatk\u0119.",
      "answer_d": "salamander i kuter.",
      "media": "",
      "code_id": 6
    }
  },
  {
    "model": "leszek_app.Question",
    "fields": {
      "question": "Oblicz cen\u0119 gastronomiczn\u0105 netto uroczystego obiadu dla jednej osoby, je\u017celi koszt zakupu surowc\u00f3w do przygotowania obiadu dla 15 os\u00f3b wynosi 240,00 z\u0142 i zak\u0142ad stosuje mar\u017c\u0119 gastronomiczn\u0105 w wysoko\u015bci 150 %.",
      "answer_a": "40,00 z\u0142",
      "answer_b": "75,00 z\u0142",
      "answer_c": "56,00 z\u0142",
      "answer_d": "31,00 z\u0142",
      "media": "",
      "code_id": 6
    }
  },
  {
    "model": "leszek_app.Question",
    "fields": {
      "question": "Na podstawie wzor\u00f3w zamieszczonych w tabeli, oblicz podstawow\u0105 przemian\u0119 materii dla kobiety w wieku 20 lat i masie cia\u0142a 55 kg.",
      "answer_a": "1 301,59 kcal/dob\u0119",
      "answer_b": "1 520,34 kcal/dob\u0119",
      "answer_c": "1 603,23 kcal/dob\u0119",
      "answer_d": "1 428,72 kcal/dob\u0119",
      "media": "f0730000-bb04-7aea-ea31-08dae134f8e6.jpg",
      "code_id": 6
    }
  },
  {
    "model": "leszek_app.Question",
    "fields": {
      "question": "Do sporz\u0105dzenia kremu bawarskiego, opr\u00f3cz jaj, mleka, cukru, \u017celatyny nale\u017cy u\u017cy\u0107",
      "answer_a": "\u015bmietanki 30% i wanilii.",
      "answer_b": "\u015bmietanki 30% i kakao.",
      "answer_c": "mas\u0142a i wanilii.",
      "answer_d": "mas\u0142a i kakao.",
      "media": "",
      "code_id": 5
    }
  },
  {
    "model": "leszek_app.Question",
    "fields": {
      "question": "Ile procent ubytku surowego ud\u017aca bez ko\u015bci jest uwzgl\u0119dnione w recepturze gulaszu wo\u0142owego, je\u017celi normatyw surowcowy na 1 porcj\u0119 potrawy o masie 120 g przewiduje zu\u017cycie 150 g tego surowca?",
      "answer_a": "20 %",
      "answer_b": "10 %",
      "answer_c": "15 %",
      "answer_d": "25 %",
      "media": "",
      "code_id": 6
    }
  },
  {
    "model": "leszek_app.Question",
    "fields": {
      "question": "Kucharz ma sporz\u0105dzi\u0107 pyzy ziemniaczane z 9 kg ziemniak\u00f3w. Ile kilogram\u00f3w ziemniak\u00f3w powinien ugotowa\u0107, post\u0119puj\u0105c zgodnie z zamieszczonym sposobem wykonania pyz ziemniaczanych?",
      "answer_a": "2,5 kg",
      "answer_b": "3 kg",
      "answer_c": "5 kg",
      "answer_d": "6,5 kg",
      "media": "47ec0000-f683-928a-3e73-08dbc96f014a.jpg",
      "code_id": 5
    }
  },
  {
    "model": "leszek_app.Question",
    "fields": {
      "question": "Na kt\u00f3rej ilustracji przedstawiona jest obieraczka do ziemniak\u00f3w?",
      "answer_a": "Na ilustracji 3.",
      "answer_b": "Na ilustracji 2.",
      "answer_c": "Na ilustracji 1.",
      "answer_d": "Na ilustracji 4.",
      "media": "f0730000-bb04-7aea-763a-08db9cba7772.jpg",
      "code_id": 6
    }
  },
  {
    "model": "leszek_app.Question",
    "fields": {
      "question": "W celu przygotowania potrawy lekkostrawnej z fileta z indyka, mi\u0119so nale\u017cy podda\u0107",
      "answer_a": "duszeniu w ma\u0142ych kawa\u0142kach.",
      "answer_b": "gotowaniu w wodzie.",
      "answer_c": "sma\u017ceniu saut\u00e9 w ma\u0142ej ilo\u015bci t\u0142uszczu.",
      "answer_d": "pieczeniu w r\u0119kawie po uprzednim obsma\u017ceniu.",
      "media": "",
      "code_id": 6
    }
  },
  {
    "model": "leszek_app.Question",
    "fields": {
      "question": "Kt\u00f3ra cena potrawy uwzgl\u0119dnia rabat w wysoko\u015bci 15 %, je\u017celi cena potrawy bez rabatu wynosi 28,00 z\u0142?",
      "answer_a": "43,00 z\u0142",
      "answer_b": "13,00 z\u0142",
      "answer_c": "23,80 z\u0142",
      "answer_d": "32,20 z\u0142",
      "media": "",
      "code_id": 6
    }
  },
  {
    "model": "leszek_app.Question",
    "fields": {
      "question": "Na obni\u017canie napi\u0119cia nerwowego, popraw\u0119 pami\u0119ci i koncentracji u cz\u0142owieka wp\u0142ywa spo\u017cywanie produkt\u00f3w bogatych",
      "answer_a": "w cynk.",
      "answer_b": "w witamin\u0119 K.",
      "answer_c": "w magnez.",
      "answer_d": "w witamin\u0119 C.",
      "media": "",
      "code_id": 6
    }
  },
  {
    "model": "leszek_app.Question",
    "fields": {
      "question": "Podczas sporz\u0105dzania mizerii zachodzi zjawisko",
      "answer_a": "oddychania.",
      "answer_b": "osmozy.",
      "answer_c": "dojrzewania.",
      "answer_d": "transpiracji.",
      "media": "",
      "code_id": 5
    }
  },
  {
    "model": "leszek_app.Question",
    "fields": {
      "question": "Mleko utrwalone metod\u0105 UHT charakteryzuje si\u0119",
      "answer_a": "mo\u017cliwo\u015bci\u0105 jego spo\u017cycia bez uprzedniego gotowania.",
      "answer_b": "zachowaniem cech mleka surowego.",
      "answer_c": "zwi\u0119kszon\u0105 zawarto\u015bci\u0105 bakterii kwasu mlekowego.",
      "answer_d": "zwi\u0119kszon\u0105 zawarto\u015bci\u0105 witaminy C.",
      "media": "",
      "code_id": 5
    }
  },
  {
    "model": "leszek_app.Question",
    "fields": {
      "question": "Papryka konserwowa zosta\u0142a otrzymana w wyniku utrwalenia papryki \u015bwie\u017cej metod\u0105 chemiczn\u0105 oraz",
      "answer_a": "termizacji.",
      "answer_b": "ultrafiltracji.",
      "answer_c": "pasteryzacji.",
      "answer_d": "liofilizacji.",
      "media": "",
      "code_id": 5
    }
  },
  {
    "model": "leszek_app.Question",
    "fields": {
      "question": "Kt\u00f3ra technika przygotowania da\u0144 z mi\u0119sa przedstawiona jest w zamieszczonym materiale filmowym?",
      "answer_a": "Tablerowanie.",
      "answer_b": "Deglasowanie.",
      "answer_c": "Flambirowanie.",
      "answer_d": "Filetowanie.",
      "media": "24480000-5d64-0015-f949-08d90bda25cc.mp4",
      "code_id": 5
    }
  },
  {
    "model": "leszek_app.Question",
    "fields": {
      "question": "Na podstawie danych zamieszczonych w tabeli, oblicz warto\u015b\u0107 energetyczn\u0105 150 g banan\u00f3w.",
      "answer_a": "104,1 kcal",
      "answer_b": "161,25 kcal",
      "answer_c": "156,15 kcal",
      "answer_d": "111,0 kcal",
      "media": "47ec0000-f683-928a-ad3b-08dbf7b63301.jpg",
      "code_id": 6
    }
  },
  {
    "model": "leszek_app.Question",
    "fields": {
      "question": "Do sporz\u0105dzenia ciasta na pierogi leniwe, opr\u00f3cz ugotowanych ziemniak\u00f3w, jaj, m\u0105ki pszennej i m\u0105ki ziemniaczanej, nale\u017cy zastosowa\u0107 ",
      "answer_a": "mas\u0142o.",
      "answer_b": "ser podpuszczkowy.",
      "answer_c": "smalec.",
      "answer_d": "ser twarogowy.",
      "media": "",
      "code_id": 6
    }
  },
  {
    "model": "leszek_app.Question",
    "fields": {
      "question": "Do grupy bia\u0142ek nale\u017c\u0105",
      "answer_a": "kolagen i niacyna.",
      "answer_b": "tokoferol i niacyna.",
      "answer_c": "tokoferol i elastyna.",
      "answer_d": "kolagen i elastyna.",
      "media": "",
      "code_id": 6
    }
  },
  {
    "model": "leszek_app.Question",
    "fields": {
      "question": "Kt\u00f3ry z wymienionych zestaw\u00f3w obiadowych jest odpowiedni dla osoby na diecie bezlaktozowej?",
      "answer_a": "Zestaw II.",
      "answer_b": "Zestaw III.",
      "answer_c": "Zestaw IV.",
      "answer_d": "Zestaw I.",
      "media": "f0730000-bb04-7aea-78bc-08db9cb89e6f.jpg",
      "code_id": 6
    }
  },
  {
    "model": "leszek_app.Question",
    "fields": {
      "question": "Restauracja przestrzega zasad zr\u00f3wnowa\u017conego rozwoju, je\u017celi u\u017cywa produkt\u00f3w",
      "answer_a": "pochodz\u0105cych z lokalnych upraw.",
      "answer_b": "wysokoprzetworzonych.",
      "answer_c": "trudno dost\u0119pnych, utrwalonych metodami fizycznymi.",
      "answer_d": "importowanych.",
      "media": "",
      "code_id": 6
    }
  },
  {
    "model": "leszek_app.Question",
    "fields": {
      "question": "Przedstawione na rysunku po\u0142o\u017cenie jaja podczas pr\u00f3by wodnej wskazuje na jajo",
      "answer_a": "zepsute.",
      "answer_b": "przechowywane 21 dni.",
      "answer_c": "\u015bwie\u017ce.",
      "answer_d": "przechowywane 15 dni.",
      "media": "24480000-5d64-0015-dcc3-08d90bd380a8.PNG",
      "code_id": 5
    }
  },
  {
    "model": "leszek_app.Question",
    "fields": {
      "question": "Kt\u00f3r\u0105 z wymienionych czynno\u015bci nale\u017cy wpisa\u0107 w schemacie blokowym sporz\u0105dzania sosu pomidorowego w miejscu oznaczonym znakiem zapytania?",
      "answer_a": "Blanszowanie pomidor\u00f3w.",
      "answer_b": "Zag\u0119szczenie sosu.",
      "answer_c": "Zabielenie sosu.",
      "answer_d": "Blendowanie pomidor\u00f3w.",
      "media": "47ec0000-f683-928a-7959-08dbf7c011b9.jpg",
      "code_id": 6
    }
  },
  {
    "model": "leszek_app.Question",
    "fields": {
      "question": "Oblicz ca\u0142kowit\u0105 przemian\u0119 materii (CPM) kobiety w wieku 44 lat o wzro\u015bcie 158 cm i masie cia\u0142a 58 kg wiedz\u0105c, \u017ce jej podstawowa przemiana materii (PPM) wynosi 1299,5 kcal/dob\u0119, a wsp\u00f3\u0142czynnik aktywno\u015bci fizycznej (PAL) 1,6.",
      "answer_a": "2741,0 kcal/dob\u0119",
      "answer_b": "1515,5 kcal/dob\u0119",
      "answer_c": "1457,5 kcal/dob\u0119",
      "answer_d": "2079,2 kcal/dob\u0119",
      "media": "",
      "code_id": 6
    }
  },
  {
    "model": "leszek_app.Question",
    "fields": {
      "question": "W wyniku zbyt d\u0142ugiego przechowywania natki pietruszki nast\u0119puje obni\u017cenie jej warto\u015bci od\u017cywczej spowodowane utrat\u0105",
      "answer_a": "b\u0142onnika.",
      "answer_b": "witaminy C.",
      "answer_c": "witaminy K.",
      "answer_d": "chlorofilu.",
      "media": "",
      "code_id": 5
    }
  },
  {
    "model": "leszek_app.Question",
    "fields": {
      "question": "Ile wynosi cena brutto 150 obiad\u00f3w w sto\u0142\u00f3wce pracowniczej, je\u017celi cena gastronomiczna netto 1 porcji wynosi 11,00 z\u0142, a podatek VAT 8 %.",
      "answer_a": "1380,00 z\u0142",
      "answer_b": "1782,00 z\u0142",
      "answer_c": "1518,00 z\u0142",
      "answer_d": "1620,00 z\u0142",
      "media": "",
      "code_id": 6
    }
  },
  {
    "model": "leszek_app.Question",
    "fields": {
      "question": "Spadek wilgotno\u015bci powietrza w magazynie ziemniak\u00f3w do poziomu 60-70% powoduje",
      "answer_a": "poch\u0142anianie pary wodnej przez ziemniaki.",
      "answer_b": "zwi\u0119kszenie zawarto\u015bci witaminy C w ziemniakach.",
      "answer_c": "du\u017ce ubytki naturalne ziemniak\u00f3w.",
      "answer_d": "rozk\u0142ad skrobi w ziemniakach.",
      "media": "",
      "code_id": 5
    }
  },
  {
    "model": "leszek_app.Question",
    "fields": {
      "question": "Kucharz przygotowuj\u0105c ciasto nale\u015bnikowe, powinien kolejno:",
      "answer_a": "wymiesza\u0107 wod\u0119 z mlekiem, doda\u0107 jaja, s\u00f3l, dobrze wyrobi\u0107 i ustali\u0107 m\u0105k\u0105 g\u0119sto\u015b\u0107 ciasta.",
      "answer_b": "do wody doda\u0107 jaja, s\u00f3l, m\u0105k\u0119, dobrze wyrobi\u0107 i ustali\u0107 mlekiem g\u0119sto\u015b\u0107 ciasta.",
      "answer_c": "wymiesza\u0107 mleko z jajami, doda\u0107 m\u0105k\u0119, s\u00f3l, dobrze wyrobi\u0107 i ustali\u0107 wod\u0105 g\u0119sto\u015b\u0107 ciasta.",
      "answer_d": "do m\u0105ki doda\u0107 jaja, s\u00f3l, wod\u0119, dobrze wyrobi\u0107 i ustali\u0107 mlekiem g\u0119sto\u015b\u0107 ciasta.",
      "media": "",
      "code_id": 5
    }
  },
  {
    "model": "leszek_app.Question",
    "fields": {
      "question": "Wykonuj\u0105c obr\u00f3bk\u0119 wst\u0119pn\u0105 drobiu wed\u0142ug opisu zamieszczonego w tabeli, tuszk\u0119 nale\u017cy",
      "answer_a": "uformowa\u0107 sposobem angielskim.",
      "answer_b": "uformowa\u0107 w kiesze\u0144.",
      "answer_c": "spi\u0105\u0107 jedn\u0105 nitk\u0105.",
      "answer_d": "spi\u0105\u0107 dwiema nitkami.",
      "media": "24480000-5d64-0015-176f-08d90bdbe1cb.PNG",
      "code_id": 5
    }
  },
  {
    "model": "leszek_app.Question",
    "fields": {
      "question": "Kt\u00f3rym obrusem, zgodnie z zasadami obs\u0142ugi go\u015bci, nale\u017cy nakry\u0107 st\u00f3\u0142 o wymiarach 120 cm x 80 cm na przyj\u0119cie zasiadane?",
      "answer_a": "180 cm x 140 cm",
      "answer_b": "150 cm x 110 cm",
      "answer_c": "150 cm x 120 cm",
      "answer_d": "180 cm x 150 cm",
      "media": "",
      "code_id": 6
    }
  },
  {
    "model": "leszek_app.Question",
    "fields": {
      "question": "Ile litr\u00f3w wody nale\u017cy odmierzy\u0107 do przygotowania 3 kg kaszy gryczanej na sypko, je\u017celi stosunek kaszy do wody wynosi 1:1,5?",
      "answer_a": "5,5 l",
      "answer_b": "3,5 l",
      "answer_c": "2,5 l",
      "answer_d": "4,5 l",
      "media": "",
      "code_id": 5
    }
  },
  {
    "model": "leszek_app.Question",
    "fields": {
      "question": "Kt\u00f3rym serwisem s\u0105 podawane owoce w za\u0142\u0105czonym materiale filmowym?",
      "answer_a": "Rosyjskim.",
      "answer_b": "Angielskim.",
      "answer_c": "Niemieckim.",
      "answer_d": "Francuskim.",
      "media": "47ec0000-f683-928a-0367-08dc9762463b.mp4",
      "code_id": 6
    }
  },
  {
    "model": "leszek_app.Question",
    "fields": {
      "question": "Na kt\u00f3rej ilustracji przedstawiony jest znak ostrzegawczy dotycz\u0105cy zagro\u017cenia pora\u017cenia pr\u0105dem elektrycznym?",
      "answer_a": "Na ilustracji I.",
      "answer_b": "Na ilustracji II.",
      "answer_c": "Na ilustracji IV.",
      "answer_d": "Na ilustracji III.",
      "media": "47ec0000-f683-928a-c335-08dc973cfd92.jpg",
      "code_id": 6
    }
  },
  {
    "model": "leszek_app.Question",
    "fields": {
      "question": "W kt\u00f3rej diecie wegetaria\u0144skiej dopuszcza si\u0119 spo\u017cywanie mleka i jego przetwor\u00f3w?",
      "answer_a": "Witaria\u0144skiej.",
      "answer_b": "Laktowegetaria\u0144skiej.",
      "answer_c": "Owowegetaria\u0144skiej.",
      "answer_d": "Frutaria\u0144skiej.",
      "media": "",
      "code_id": 6
    }
  },
  {
    "model": "leszek_app.Question",
    "fields": {
      "question": "Namoczona i odci\u015bni\u0119ta bu\u0142ka dodana do mi\u0119snej masy mielonej jest w niej sk\u0142adnikiem",
      "answer_a": "g\u0142\u00f3wnym.",
      "answer_b": "sklejaj\u0105cym.",
      "answer_c": "smakowym.",
      "answer_d": "spulchniaj\u0105cym.",
      "media": "",
      "code_id": 5
    }
  },
  {
    "model": "leszek_app.Question",
    "fields": {
      "question": "Na kt\u00f3rej ilustracji przedstawione jest naczynie do serwowania galaretki owocowej?",
      "answer_a": "Na ilustracji 1.",
      "answer_b": "Na ilustracji 2.",
      "answer_c": "Na ilustracji 3.",
      "answer_d": "Na ilustracji 4.",
      "media": "24480000-5d64-0015-2f76-08d90bddbd58.PNG",
      "code_id": 5
    }
  },
  {
    "model": "leszek_app.Question",
    "fields": {
      "question": "Na ilustracji przedstawiony jest dojrza\u0142y owoc",
      "answer_a": "papai.",
      "answer_b": "figi.",
      "answer_c": "mango.",
      "answer_d": "marakui.",
      "media": "24480000-5d64-0015-a41a-08d90bccd867.PNG",
      "code_id": 5
    }
  },
  {
    "model": "leszek_app.Question",
    "fields": {
      "question": "Kt\u00f3re nakrycie nale\u017cy przygotowa\u0107 do zestawu potraw podawanych serwisem francuskim: zupy borowikowej, pieczeni wo\u0142owej w sosie w\u0142asnym, pur\u00e9e ziemniaczanego, burak\u00f3w zasma\u017canych i piernika?",
      "answer_a": "Nakrycie 4.",
      "answer_b": "Nakrycie 1.",
      "answer_c": "Nakrycie 3.",
      "answer_d": "Nakrycie 2.",
      "media": "f0730000-bb04-7aea-edb6-08db98d0199c.jpg",
      "code_id": 6
    }
  },
  {
    "model": "leszek_app.Question",
    "fields": {
      "question": "Enzymy z grupy lipaz s\u0105 odpowiedzialne w organizmie cz\u0142owieka za trawienie",
      "answer_a": "bia\u0142ek.",
      "answer_b": "skrobi.",
      "answer_c": "t\u0142uszcz\u00f3w.",
      "answer_d": "sacharozy.",
      "media": "",
      "code_id": 6
    }
  },
  {
    "model": "leszek_app.Question",
    "fields": {
      "question": "W zak\u0142adach gastronomicznych, opieraj\u0105c si\u0119 na zasadach systemu HACCP do obr\u00f3bki wst\u0119pnej surowego drobiu nale\u017cy stosowa\u0107 desk\u0119 koloru",
      "answer_a": "zielonego.",
      "answer_b": "niebieskiego.",
      "answer_c": "\u017c\u00f3\u0142tego.",
      "answer_d": "bia\u0142ego.",
      "media": "",
      "code_id": 5
    }
  },
  {
    "model": "leszek_app.Question",
    "fields": {
      "question": "Korzystaj\u0105c z normatyw\u00f3w surowcowych zamieszczonych w tabeli, oblicz zapotrzebowanie na surowce niezb\u0119dne do przygotowania 5 porcji sufletu i 12 porcji kompotu.",
      "answer_a": "Jab\u0142ka 1,80 kg, mas\u0142o 0,25 kg, cukier 0,58 kg, jajo 4 szt.",
      "answer_b": "Jab\u0142ka 1,80 kg, mas\u0142o 0,60 kg, cukier 0,58 kg, jajo 10 szt.",
      "answer_c": "Jab\u0142ka 1,96 kg, mas\u0142o 0,60 kg, cukier 0,44 kg, jajo 4 szt.",
      "answer_d": "Jab\u0142ka 1,96 kg, mas\u0142o 0,25 kg, cukier 0,44 kg, jajo 10 szt.",
      "media": "f0730000-bb04-7aea-925b-08dae135e1be.jpg",
      "code_id": 6
    }
  },
  {
    "model": "leszek_app.Question",
    "fields": {
      "question": "Warto\u015b\u0107 mar\u017cy gastronomicznej nie zale\u017cy od",
      "answer_a": "wysoko\u015bci podatku VAT.",
      "answer_b": "rodzaju zak\u0142adu gastronomicznego.",
      "answer_c": "wysoko\u015bci op\u0142at za u\u017cytkowanie lokalu.",
      "answer_d": "rodzaju us\u0142ug \u015bwiadczonych w restauracji.",
      "media": "",
      "code_id": 6
    }
  },
  {
    "model": "leszek_app.Question",
    "fields": {
      "question": "Oblicz warto\u015b\u0107 energetyczn\u0105 200 g papryki nadziewanej mi\u0119sem, je\u017celi 100 g tej potrawy zawiera 4 g bia\u0142ka, 10 g t\u0142uszczu i 14 g w\u0119glowodan\u00f3w.",
      "answer_a": "56 kcal",
      "answer_b": "162 kcal",
      "answer_c": "28 kcal",
      "answer_d": "324 kcal",
      "media": "",
      "code_id": 6
    }
  },
  {
    "model": "leszek_app.Question",
    "fields": {
      "question": "Kt\u00f3re urz\u0105dzenie ch\u0142odnicze stanowi podstawowe wyposa\u017cenie pomieszcze\u0144 magazynowych?",
      "answer_a": "Witryna ch\u0142odnicza.",
      "answer_b": "Lada ch\u0142odnicza.",
      "answer_c": "St\u00f3\u0142 ch\u0142odniczy.",
      "answer_d": "Szafa ch\u0142odnicza.",
      "media": "",
      "code_id": 5
    }
  },
  {
    "model": "leszek_app.Question",
    "fields": {
      "question": "Kt\u00f3ry z podanych zakres\u00f3w temperatur jest optymalny do przechowywania kiszonek?",
      "answer_a": "Od 0 \u00b0C do 5 \u00b0C",
      "answer_b": "Od 6 \u00b0C do 15 \u00b0C",
      "answer_c": "Od 18 \u00b0C do 25 \u00b0C",
      "answer_d": "Od -18 \u00b0C do -5 \u00b0C",
      "media": "",
      "code_id": 5
    }
  },
  {
    "model": "leszek_app.Question",
    "fields": {
      "question": "Do zak\u0142ad\u00f3w gastronomicznych typu \u017cywieniowego nale\u017c\u0105 wy\u0142\u0105cznie:",
      "answer_a": "bistra, jad\u0142odajnie, cukiernie.",
      "answer_b": "bary, bistra, piwiarnie.",
      "answer_c": "bary, kawiarnie, restauracje.",
      "answer_d": "bistra, jad\u0142odajnie, bary.",
      "media": "",
      "code_id": 6
    }
  },
  {
    "model": "leszek_app.Question",
    "fields": {
      "question": "Do obowi\u0105zk\u00f3w sommeliera nale\u017cy",
      "answer_a": "parzenie kawy.",
      "answer_b": "serwowanie herbaty.",
      "answer_c": "dobieranie win do potraw.",
      "answer_d": "sporz\u0105dzanie napoj\u00f3w alkoholowych.",
      "media": "",
      "code_id": 6
    }
  },
  {
    "model": "leszek_app.Question",
    "fields": {
      "question": "Na kt\u00f3rej ilustracji przedstawione jest naczynie odpowiednie do podania zupy krem z pomidor\u00f3w serwisem niemieckim?",
      "answer_a": "Na ilustracji 2.",
      "answer_b": "Na ilustracji 3.",
      "answer_c": "Na ilustracji 4.",
      "answer_d": "Na ilustracji 1.",
      "media": "47ec0000-f683-928a-886d-08dc975dd27b.jpg",
      "code_id": 6
    }
  },
  {
    "model": "leszek_app.Question",
    "fields": {
      "question": "Na kt\u00f3rej ilustracji przedstawione jest urz\u0105dzenie do wyciskania soku?",
      "answer_a": "Na ilustracji 1.",
      "answer_b": "Na ilustracji 4.",
      "answer_c": "Na ilustracji 3.",
      "answer_d": "Na ilustracji 2.",
      "media": "f0730000-bb04-7aea-6ebe-08dae1343662.jpg",
      "code_id": 6
    }
  },
  {
    "model": "leszek_app.Question",
    "fields": {
      "question": "Przek\u0105sek zimnych, zgodnie z zasadami Dobrej Praktyki Produkcyjnej, nie nale\u017cy przechowywa\u0107 d\u0142u\u017cej ni\u017c",
      "answer_a": "12 godzin w temperaturze od 2 \u00b0C do 6 \u00b0C",
      "answer_b": "24 godziny w temperaturze od 2 \u00b0C do 6 \u00b0C",
      "answer_c": "24 godziny w temperaturze od 8 \u00b0C do 12 \u00b0C",
      "answer_d": "12 godzin w temperaturze od 8 \u00b0C do 12 \u00b0C",
      "media": "",
      "code_id": 6
    }
  },
  {
    "model": "leszek_app.Question",
    "fields": {
      "question": "Us\u0142ug\u0105 podstawow\u0105 w restauracji jest",
      "answer_a": "sporz\u0105dzanie potraw.",
      "answer_b": "organizowanie przyj\u0119\u0107.",
      "answer_c": "sprzeda\u017c potraw na wynos.",
      "answer_d": "catering dietetyczny.",
      "media": "",
      "code_id": 6
    }
  },
  {
    "model": "leszek_app.Question",
    "fields": {
      "question": "Potraw\u0105 lekkostrawn\u0105 s\u0105",
      "answer_a": "zrazy wo\u0142owe bite w sosie w\u0142asnym.",
      "answer_b": "roladki jagni\u0119ce w sosie my\u015bliwskim.",
      "answer_c": "klopsiki wieprzowe w sosie cebulowym.",
      "answer_d": "pulpety ciel\u0119ce w sosie koperkowym.",
      "media": "",
      "code_id": 5
    }
  },
  {
    "model": "leszek_app.Question",
    "fields": {
      "question": "Do sporz\u0105dzania kt\u00f3rych klusek nale\u017cy u\u017cy\u0107 dro\u017cd\u017cy?",
      "answer_a": "Francuskich.",
      "answer_b": "Zacierek.",
      "answer_c": "Leniwych.",
      "answer_d": "Pampuch\u00f3w.",
      "media": "",
      "code_id": 5
    }
  },
  {
    "model": "leszek_app.Question",
    "fields": {
      "question": "Kt\u00f3ra z wymienionych grup produkt\u00f3w jest dla cz\u0142owieka \u017ar\u00f3d\u0142em bia\u0142ka ro\u015blinnego?",
      "answer_a": "Fasola, mleko, groch.",
      "answer_b": "Ciecierzyca, fasola, b\u00f3b.",
      "answer_c": "Soczewica, ser, b\u00f3b.",
      "answer_d": "Groch, soja, jajo.",
      "media": "",
      "code_id": 6
    }
  },
  {
    "model": "leszek_app.Question",
    "fields": {
      "question": "Na podstawie danych zamieszczonych w tabeli, oblicz zapotrzebowanie na surowce niezb\u0119dne do sporz\u0105dzenia 25 porcji ziemniak\u00f3w pieczonych.",
      "answer_a": "Ziemniaki 3,75 kg, czosnek 1,25 kg, olej rzepakowy 2,5 l",
      "answer_b": "Ziemniaki 2,25 kg, czosnek 0,075 kg, olej rzepakowy 0,25 l",
      "answer_c": "Ziemniaki 3,75 kg, czosnek 0,125 kg, olej rzepakowy 0,25 l",
      "answer_d": "Ziemniaki 2,25 kg, czosnek 0,75 kg, olej rzepakowy 2,5 l",
      "media": "f0730000-bb04-7aea-e2ec-08db980838f6.jpg",
      "code_id": 6
    }
  },
  {
    "model": "leszek_app.Question",
    "fields": {
      "question": "Kt\u00f3r\u0105 z wymienionych czynno\u015bci powinien wykona\u0107 kelner podchodz\u0105c z lewej strony go\u015bcia podczas przyj\u0119cia zasiadanego?",
      "answer_a": "Podanie przystawki wyporcjowanej na talerzu.",
      "answer_b": "Nalewanie kawy z dzbanka do fili\u017canki.",
      "answer_c": "Nalewanie zupy z wazy do talerza g\u0142\u0119bokiego.",
      "answer_d": "Podanie wina w kieliszku.",
      "media": "",
      "code_id": 6
    }
  },
  {
    "model": "leszek_app.Question",
    "fields": {
      "question": "Na kt\u00f3rej ilustracji przedstawione s\u0105 nasiona soczewicy?",
      "answer_a": "Na ilustracji 3.",
      "answer_b": "Na ilustracji 2.",
      "answer_c": "Na ilustracji 4.",
      "answer_d": "Na ilustracji 1.",
      "media": "24480000-5d64-0015-e597-08d90bcd0d7e.PNG",
      "code_id": 5
    }
  },
  {
    "model": "leszek_app.Question",
    "fields": {
      "question": "Kt\u00f3r\u0105 z wymienionych potraw nale\u017cy zaplanowa\u0107 w karcie restauracji dla os\u00f3b stosuj\u0105cych diet\u0119 ichtiwegetaria\u0144sk\u0105?",
      "answer_a": "Ryba po kaszubsku.",
      "answer_b": "Tarta z wieprzowin\u0105.",
      "answer_c": "Paella z kurczakiem.",
      "answer_d": "Wo\u0142owina po burgundzku.",
      "media": "",
      "code_id": 6
    }
  },
  {
    "model": "leszek_app.Question",
    "fields": {
      "question": "Postawa cia\u0142a przedstawiona na rysunku, w komunikacji niewerbalnej oznacza",
      "answer_a": "pewno\u015b\u0107 siebie.",
      "answer_b": "zmartwienie.",
      "answer_c": "zadowolenie.",
      "answer_d": "rado\u015b\u0107.",
      "media": "24480000-5d64-0015-82ec-08d90bde4397.PNG",
      "code_id": 5
    }
  },
  {
    "model": "leszek_app.Question",
    "fields": {
      "question": "Kt\u00f3rego dnia najp\u00f3\u017aniej nale\u017cy wykona\u0107 przelew za faktur\u0119 z 7-dniowym terminem p\u0142atno\u015bci, wystawion\u0105 w dniu wykonania us\u0142ugi tj. 24 wrze\u015bnia 20XX roku?",
      "answer_a": "01.10.20XX r.",
      "answer_b": "29.09.20XX r.",
      "answer_c": "30.09.20XX r.",
      "answer_d": "02.10.20XX r.",
      "media": "",
      "code_id": 6
    }
  },
  {
    "model": "leszek_app.Question",
    "fields": {
      "question": "Kt\u00f3r\u0105 funkcj\u0119 w organizmie cz\u0142owieka pe\u0142ni b\u0142onnik pokarmowy?",
      "answer_a": "Reguluje r\u00f3wnowag\u0119 kwasowo-zasadow\u0105.",
      "answer_b": "Zwi\u0119ksza aktywno\u015b\u0107 motoryczn\u0105 jelit.",
      "answer_c": "Zwi\u0119ksza zawarto\u015b\u0107 cholesterolu we krwi.",
      "answer_d": "Wp\u0142ywa na prawid\u0142owy rytm pracy serca.",
      "media": "",
      "code_id": 6
    }
  },
  {
    "model": "leszek_app.Question",
    "fields": {
      "question": "Na podstawie danych zamieszczonych w tabeli, oblicz zawarto\u015b\u0107 bia\u0142ka zwierz\u0119cego w 1 porcji omletu sporz\u0105dzonego ze 100 g jaj, 10 g mas\u0142a, 20 g szynki wieprzowej i 50 g groszku zielonego.",
      "answer_a": "20,82 g",
      "answer_b": "15,85 g",
      "answer_c": "16,48 g",
      "answer_d": "19,20 g",
      "media": "47ec0000-f683-928a-f922-08dbf7b5b4f1.jpg",
      "code_id": 6
    }
  },
  {
    "model": "leszek_app.Question",
    "fields": {
      "question": "Kt\u00f3r\u0105 metod\u0119 obs\u0142ugi nale\u017cy zastosowa\u0107 do podania zupy w wazie grupie dzieci w sto\u0142\u00f3wce szkolnej?",
      "answer_a": "Niemieck\u0105.",
      "answer_b": "Rosyjsk\u0105.",
      "answer_c": "Francusk\u0105.",
      "answer_d": "Angielsk\u0105.",
      "media": "",
      "code_id": 6
    }
  },
  {
    "model": "leszek_app.Question",
    "fields": {
      "question": "Na podstawie danych zamieszczonych w tabeli oblicz, ile kilogram\u00f3w pieczeni otrzyma si\u0119 z rostbefu o masie 3,5 kg.",
      "answer_a": "2,45 kg",
      "answer_b": "2,80 kg",
      "answer_c": "2,63 kg",
      "answer_d": "2,10 kg",
      "media": "f0730000-bb04-7aea-ae15-08db98cd3a12.jpg",
      "code_id": 6
    }
  },
  {
    "model": "leszek_app.Question",
    "fields": {
      "question": "Do konsumpcji \u015bniadania wiede\u0144skiego nale\u017cy poda\u0107 widelce i no\u017ce sto\u0142owe",
      "answer_a": "specjalne.",
      "answer_b": "du\u017ce.",
      "answer_c": "\u015brednie.",
      "answer_d": "ma\u0142e.",
      "media": "",
      "code_id": 6
    }
  }
]
